spark_etl/__init__.py
spark_etl/application.py
spark_etl/build.py
spark_etl/cmds.py
spark_etl/exceptions.py
spark_etl/misc_tools.py
spark_etl/ssh_config.py
spark_etl/template.py
spark_etl/utils.py
spark_etl/version.py
spark_etl/core/__init__.py
spark_etl/core/hdfs_client.py
spark_etl/core/local_client.py
spark_etl/core/main.py
spark_etl/core/s3_client.py
spark_etl/core/loader_util/resources/job_loader.py
spark_etl/deployers/__init__.py
spark_etl/deployers/abstract_deployer.py
spark_etl/deployers/hdfs_deployer.py
spark_etl/deployers/job_loader.py
spark_etl/deployers/s3_deployer.py
spark_etl/job_submitters/__init__.py
spark_etl/job_submitters/abstract_job_submitter.py
spark_etl/job_submitters/livy_job_submitter.py
spark_etl/vendors/__init__.py
spark_etl/vendors/local/__init__.py
spark_etl/vendors/local/local_deployer.py
spark_etl/vendors/local/pyspark_job_submitter.py
spark_etl/vendors/oracle/__init__.py
spark_etl/vendors/oracle/dataflow_deployer.py
spark_etl/vendors/oracle/dataflow_job_submitter.py
spark_etl/vendors/oracle/job_loader.py
spark_etl/vendors/oracle/tools.py
spark_etl-0.0.130.dist-info/LICENSE
spark_etl-0.0.130.dist-info/METADATA
spark_etl-0.0.130.dist-info/WHEEL
spark_etl-0.0.130.dist-info/entry_points.txt
spark_etl-0.0.130.dist-info/top_level.txt
spark_etl-0.0.130.dist-info/RECORD
