Metadata-Version: 2.1
Name: spark-etl
Version: 0.0.130
Summary: Generic ETL Pipeline Framework for Apache Spark
Home-page: https://github.com/stonezhong/spark_etl
Author: Stone Zhong
Author-email: stonezhong@hotmail.com
License: MIT
Classifier: License :: OSI Approved :: MIT License
Classifier: Programming Language :: Python :: 3
License-File: LICENSE
Requires-Dist: requests
Requires-Dist: Jinja2
Requires-Dist: termcolor
